{
  "indexes": [
    {
      "collectionGroup": "courseTopics",
      "queryScope": "COLLECTION",
      "fields": [
        {
          "fieldPath": "courseId",
          "order": "ASCENDING"
        },
        {
          "fieldPath": "order",
          "order": "ASCENDING"
        }
      ]
    },
    {
      "collectionGroup": "courseQuestions",
      "queryScope": "COLLECTION",
      "fields": [
        {
          "fieldPath": "courseId",
          "order": "ASCENDING"
        },
        {
          "fieldPath": "order",
          "order": "ASCENDING"
        },
        {
          "fieldPath": "createdAt",
          "order": "DESCENDING"
        }
      ]
    },
    {
      "collectionGroup": "courseQuestions",
      "queryScope": "COLLECTION",
      "fields": [
        {
          "fieldPath": "courseId",
          "order": "ASCENDING"
        },
        {
          "fieldPath": "topicId",
          "order": "ASCENDING"
        },
        {
          "fieldPath": "order",
          "order": "ASCENDING"
        }
      ]
    },
    {
      "collectionGroup": "courseQuestions",
      "queryScope": "COLLECTION",
      "fields": [
        {
          "fieldPath": "courseId",
          "order": "ASCENDING"
        },
        {
          "fieldPath": "difficulty",
          "order": "ASCENDING"
        },
        {
          "fieldPath": "order",
          "order": "ASCENDING"
        }
      ]
    },
    {
      "collectionGroup": "courseQuestions",
      "queryScope": "COLLECTION",
      "fields": [
        {
          "fieldPath": "courseId",
          "order": "ASCENDING"
        },
        {
          "fieldPath": "type",
          "order": "ASCENDING"
        },
        {
          "fieldPath": "order",
          "order": "ASCENDING"
        }
      ]
    },
    {
      "collectionGroup": "courseQuestions",
      "queryScope": "COLLECTION",
      "fields": [
        {
          "fieldPath": "courseId",
          "order": "ASCENDING"
        },
        {
          "fieldPath": "flags.important",
          "order": "ASCENDING"
        },
        {
          "fieldPath": "order",
          "order": "ASCENDING"
        }
      ]
    },
    {
      "collectionGroup": "courseQuestions",
      "queryScope": "COLLECTION",
      "fields": [
        {
          "fieldPath": "courseId",
          "order": "ASCENDING"
        },
        {
          "fieldPath": "flags.frequently_asked",
          "order": "ASCENDING"
        },
        {
          "fieldPath": "order",
          "order": "ASCENDING"
        }
      ]
    },
    {
      "collectionGroup": "courseQuestions",
      "queryScope": "COLLECTION",
      "fields": [
        {
          "fieldPath": "courseId",
          "order": "ASCENDING"
        },
        {
          "fieldPath": "flags.practical",
          "order": "ASCENDING"
        },
        {
          "fieldPath": "order",
          "order": "ASCENDING"
        }
      ]
    },
    {
      "collectionGroup": "courseQuestions",
      "queryScope": "COLLECTION",
      "fields": [
        {
          "fieldPath": "courseId",
          "order": "ASCENDING"
        },
        {
          "fieldPath": "flags.conceptual",
          "order": "ASCENDING"
        },
        {
          "fieldPath": "order",
          "order": "ASCENDING"
        }
      ]
    },
    {
      "collectionGroup": "courseQuestions",
      "queryScope": "COLLECTION",
      "fields": [
        {
          "fieldPath": "courseId",
          "order": "ASCENDING"
        },
        {
          "fieldPath": "marks",
          "order": "ASCENDING"
        },
        {
          "fieldPath": "order",
          "order": "ASCENDING"
        }
      ]
    },
    {
      "collectionGroup": "activities",
      "queryScope": "COLLECTION",
      "fields": [
        {
          "fieldPath": "instructorId",
          "order": "ASCENDING"
        },
        {
          "fieldPath": "createdAt",
          "order": "DESCENDING"
        }
      ]
    },
    {
      "collectionGroup": "programs",
      "queryScope": "COLLECTION",
      "fields": [
        {
          "fieldPath": "collegeId",
          "order": "ASCENDING"
        },
        {
          "fieldPath": "isActive",
          "order": "ASCENDING"
        },
        {
          "fieldPath": "name",
          "order": "ASCENDING"
        }
      ]
    }
  ],
  "fieldOverrides": []
}
